coordpy/__init__.py
coordpy-1.0.0.dist-info/licenses/LICENSE
coordpy-1.0.0.dist-info/METADATA
coordpy-1.0.0.dist-info/WHEEL
coordpy-1.0.0.dist-info/top_level.txt
coordpy-1.0.0.dist-info/RECORD
