Metadata-Version: 2.4
Name: coordpy
Version: 1.0.0
Summary: Provides a class for geographic coordinate
Author-email: Ngô Trần Quang Thiện <quangthienngotran@gmail.com>
License: GPLv3
Keywords: geography, coordinate
Requires-Python: >=3.7
License-File: LICENSE
Dynamic: license-file
